exon_py/__about__.py
exon_py/__init__.py
exon_py/proto/__init__.py
exon_py/proto/exome/__init__.py
exon_py/proto/exome/v1/__init__.py
exon_py/proto/exome/v1/catalog_pb2.py
exon_py/proto/exome/v1/catalog_pb2.pyi
exon_py/proto/exome/v1/catalog_pb2_grpc.py
exon_py/proto/exome/v1/health_check_pb2.py
exon_py/proto/exome/v1/health_check_pb2.pyi
exon_py/proto/exome/v1/health_check_pb2_grpc.py
exon_py-0.1.0.dist-info/METADATA
exon_py-0.1.0.dist-info/WHEEL
exon_py-0.1.0.dist-info/licenses/LICENSE.txt
exon_py-0.1.0.dist-info/RECORD
