Metadata-Version: 2.1
Name: exon-py
Version: 0.1.0
Project-URL: Documentation, https://github.com/unknown/exon-py#readme
Project-URL: Issues, https://github.com/unknown/exon-py/issues
Project-URL: Source, https://github.com/unknown/exon-py
Author-email: Trent Hauck <trent@trenthauck.com>
License-Expression: MIT
License-File: LICENSE.txt
Classifier: Programming Language :: Python
Classifier: Programming Language :: Python :: 3.9
Classifier: Programming Language :: Python :: 3.10
Classifier: Programming Language :: Python :: 3.11
Classifier: Programming Language :: Python :: 3.12
Classifier: Programming Language :: Python :: Implementation :: CPython
Classifier: Programming Language :: Python :: Implementation :: PyPy
Requires-Python: >=3.9
Requires-Dist: adbc-driver-flightsql==0.8.0
Requires-Dist: grpcio==1.59.3
Requires-Dist: protobuf==4.25.1
Requires-Dist: pyarrow==14.0.1
